lonny_aws_procs/__init__.py
lonny_aws_procs/__main__.py
lonny_aws_procs/action.py
lonny_aws_procs/logger.py
lonny_aws_procs/type.py
lonny_aws_procs-0.1.7.dist-info/WHEEL
lonny_aws_procs-0.1.7.dist-info/METADATA
lonny_aws_procs-0.1.7.dist-info/RECORD
