Metadata-Version: 2.1
Name: lonny-aws-procs
Version: 0.1.7
Summary: 
Author: tlonny
Author-email: t@lonny.io
Requires-Python: >=3.8,<4.0
Classifier: Programming Language :: Python :: 3
Classifier: Programming Language :: Python :: 3.8
Requires-Dist: boto3 (>=1.14.16,<2.0.0)
